adxp_sdk/__init__.py
adxp_sdk/agents/__init__.py
adxp_sdk/agents/app_client.py
adxp_sdk/agents/graph_builder.py
adxp_sdk/agents/graph_client.py
adxp_sdk/agents/graph_schemas.py
adxp_sdk/agents/graph_utils.py
adxp_sdk/agents/trace.py
adxp_sdk/apikey/__init__.py
adxp_sdk/apikey/hub.py
adxp_sdk/auth/__init__.py
adxp_sdk/auth/credentials.py
adxp_sdk/authorization/hub.py
adxp_sdk/authorization/utils.py
adxp_sdk/dataset/__init__.py
adxp_sdk/dataset/hub.py
adxp_sdk/dataset/schemas.py
adxp_sdk/finetuning/__init__.py
adxp_sdk/finetuning/base_hub.py
adxp_sdk/finetuning/hub.py
adxp_sdk/finetuning/schemas.py
adxp_sdk/finetuning/utils.py
adxp_sdk/knowledges/__init__.py
adxp_sdk/knowledges/constants.py
adxp_sdk/knowledges/enums.py
adxp_sdk/knowledges/hub.py
adxp_sdk/knowledges/retriever.py
adxp_sdk/knowledges/schemas.py
adxp_sdk/lineage/__init__.py
adxp_sdk/lineage/lineage.py
adxp_sdk/models/__init__.py
adxp_sdk/models/hub.py
adxp_sdk/models/schemas.py
adxp_sdk/models/utils.py
adxp_sdk/prompts/__init__.py
adxp_sdk/prompts/hub.py
adxp_sdk/prompts/prompt_client.py
adxp_sdk/prompts/prompt_schemas.py
adxp_sdk/prompts/utils.py
adxp_sdk/serves/__init__.py
adxp_sdk/serves/enums.py
adxp_sdk/serves/graphapp_manager.py
adxp_sdk/serves/playground_login.py
adxp_sdk/serves/schema.py
adxp_sdk/serves/server.py
adxp_sdk/serves/utils.py
adxp_sdk-0.1.18.dist-info/METADATA
adxp_sdk-0.1.18.dist-info/WHEEL
adxp_sdk-0.1.18.dist-info/RECORD
