Metadata-Version: 2.4
Name: adxp-sdk
Version: 0.1.18
Summary: SDK for AIX Platform
License: Proprietary
Author: AIX Enterprise
Requires-Python: >=3.10,<4.0
Classifier: License :: Other/Proprietary License
Classifier: Programming Language :: Python :: 3
Classifier: Programming Language :: Python :: 3.10
Classifier: Programming Language :: Python :: 3.11
Classifier: Programming Language :: Python :: 3.12
Classifier: Programming Language :: Python :: 3.13
Classifier: Programming Language :: Python :: 3.14
Requires-Dist: autologging (>=1.3.2,<2.0.0)
Requires-Dist: dotenv (>=0.9.9,<0.10.0)
Requires-Dist: fastapi (>=0.115.12,<0.116.0)
Requires-Dist: gunicorn (>=23.0.0,<24.0.0)
Requires-Dist: langchain (>=0.3.0,<0.4.0)
Requires-Dist: langserve[all] (>=0.3.0,<0.4.0)
Requires-Dist: pydantic[email] (<=2.10.6)
Requires-Dist: python-multipart (>=0.0.9,<0.0.10)
Requires-Dist: sse-starlette (<2.0.0)
Requires-Dist: uvicorn (>=0.30.6,<0.31.0)
